watson/__init__.py
watson/admin.py
watson/apps.py
watson/backends.py
watson/middleware.py
watson/models.py
watson/search.py
watson/urls.py
watson/views.py
watson/management/__init__.py
watson/management/commands/__init__.py
watson/management/commands/buildwatson.py
watson/management/commands/installwatson.py
watson/management/commands/listwatson.py
watson/management/commands/uninstallwatson.py
watson/migrations/0001_initial.py
watson/migrations/__init__.py
watson/templates/watson/search_results.html
watson/templates/watson/includes/search_result_item.html
watson/templates/watson/includes/search_results.html
watson/templatetags/__init__.py
watson/templatetags/watson.py
django_watson-1.6.2.dist-info/LICENSE
django_watson-1.6.2.dist-info/METADATA
django_watson-1.6.2.dist-info/WHEEL
django_watson-1.6.2.dist-info/top_level.txt
django_watson-1.6.2.dist-info/RECORD
